mailinator/__init__.py
mailinator/authenticators.py
mailinator/base.py
mailinator/domain.py
mailinator/mailinator.py
mailinator/message.py
mailinator/models.py
mailinator/rules.py
mailinator/stats.py
mailinator/webhooks.py
tests/__init__.py
tests/test_mailinator.py
mailinator_python_client_2-0.0.8.dist-info/LICENSE
mailinator_python_client_2-0.0.8.dist-info/METADATA
mailinator_python_client_2-0.0.8.dist-info/WHEEL
mailinator_python_client_2-0.0.8.dist-info/top_level.txt
mailinator_python_client_2-0.0.8.dist-info/RECORD
