Metadata-Version: 2.2
Name: mailinator_python_client_2
Version: 0.0.8
Summary: SDK for Mailinator
Home-page: https://github.com/manybrain/mailinator-python-client
Author: Marian Melnychuk
Author-email: marian.melnychuk@gmail.com
Classifier: Programming Language :: Python :: 3
Classifier: License :: OSI Approved :: MIT License
Classifier: Operating System :: OS Independent
Requires-Python: >=3.6
License-File: LICENSE
Requires-Dist: requests
Dynamic: author
Dynamic: author-email
Dynamic: classifier
Dynamic: description
Dynamic: description-content-type
Dynamic: home-page
Dynamic: requires-dist
Dynamic: requires-python
Dynamic: summary
